flywheel_healthcare_api/__init__.py
flywheel_healthcare_api/cache.py
flywheel_healthcare_api/client.py
flywheel_healthcare_api-0.1.2.dist-info/LICENSE
flywheel_healthcare_api-0.1.2.dist-info/METADATA
flywheel_healthcare_api-0.1.2.dist-info/WHEEL
flywheel_healthcare_api-0.1.2.dist-info/top_level.txt
flywheel_healthcare_api-0.1.2.dist-info/RECORD
