Metadata-Version: 2.1
Name: flywheel-healthcare-api
Version: 0.1.2
Summary: Google Cloud Healthcare API client library
Home-page: https://github.com/flywheel-io/healthcare-api
Author-email: support@flywheel.io
License: MIT
Project-URL: Source, https://github.com/flywheel-io/healthcare-api
Keywords: Flywheel,flywheel,google,healthcare,api
Platform: UNKNOWN
Requires-Dist: requests (~=2.22.0)
Requires-Dist: google-api-python-client (~=1.7.9)
Requires-Dist: google-auth (~=1.6.3)
Provides-Extra: dev
Requires-Dist: pycodestyle (~=2.4.0) ; extra == 'dev'
Requires-Dist: pylint (~=2.3.0) ; extra == 'dev'
Requires-Dist: pytest (~=3.6.0) ; extra == 'dev'
Requires-Dist: pytest-cov (~=2.5.0) ; extra == 'dev'
Requires-Dist: pytest-mock (~=1.10.4) ; extra == 'dev'
Provides-Extra: dicomweb
Requires-Dist: dicomweb-client ; extra == 'dicomweb'
